credbl/__init__.py
credbl/credentials.py
credbl/mongodb_utils.py
credbl/odbc_utils.py
credbl-0.0.4.dist-info/METADATA
credbl-0.0.4.dist-info/WHEEL
credbl-0.0.4.dist-info/top_level.txt
credbl-0.0.4.dist-info/RECORD
