Metadata-Version: 2.1
Name: credbl
Version: 0.0.4
Summary: package for database cofiguration and credential management
Home-page: https://github.com/BCHSI/credbl
Author: Dima Lituiev
Author-email: d.lituiev@gmail.com
License: UNKNOWN
Platform: UNKNOWN
Classifier: Programming Language :: Python :: 3
Classifier: License :: OSI Approved :: MIT License
Classifier: Operating System :: OS Independent
Requires-Python: >=3.6
Requires-Dist: pymongo
Requires-Dist: pyyaml
Requires-Dist: click
Requires-Dist: keyring
Requires-Dist: keyrings.alt ; platform_system == "Linux"
